client/__init__.py
client/__main__.py
client/args.py
client/main.py
common/__init__.py
common/data.py
common/log.py
cubething_psync-0.5.0.dist-info/licenses/LICENSE
server/__init__.py
server/__main__.py
server/args.py
server/main.py
cubething_psync-0.5.0.dist-info/METADATA
cubething_psync-0.5.0.dist-info/WHEEL
cubething_psync-0.5.0.dist-info/entry_points.txt
cubething_psync-0.5.0.dist-info/top_level.txt
cubething_psync-0.5.0.dist-info/RECORD
