Metadata-Version: 2.4
Name: cubething_psync
Version: 0.5.0
Summary: Simple project synchronization tool.
Author-email: ada mandala <ada@cubething.dev>
License-Expression: MIT
Classifier: Programming Language :: Python :: 3
Classifier: Operating System :: Unix
Requires-Python: >=3.13
License-File: LICENSE
Requires-Dist: build>=1.3.0
Requires-Dist: loguru>=0.7.3
Requires-Dist: setuptools>=80.9.0
Requires-Dist: websockets>=15.0.1
Dynamic: license-file
